{
  "$schema": "https://biomejs.dev/schemas/1.5.3/schema.json",
  "files": {
    "ignore": [
      "dist",
      "playwright-report",
      "test-results",
      "*.gen.*",
      "e2e/.auth/user.json",
      "vite.config.ts.timestamp-*.mjs"
    ]
  },
  "organizeImports": {
    "enabled": true
  },
  "formatter": {
    "enabled": true,
    "indentStyle": "space"
  },
  "linter": {
    "enabled": true,
    "rules": {
      "recommended": true,
      "nursery": {
        "useSortedClasses": "error",
        "useFilenamingConvention": {
          "level": "error",
          "options": { "filenameCases": ["kebab-case"] }
        }
      }
    }
  }
}
